zarrs-0.2.1.dist-info/METADATA
zarrs-0.2.1.dist-info/WHEEL
zarrs-0.2.1.dist-info/entry_points.txt
zarrs-0.2.1.dist-info/licenses/LICENSE
zarrs/__init__.py
zarrs/_internal.abi3.so
zarrs/_internal.pyi
zarrs/pipeline.py
zarrs/py.typed
zarrs/utils.py
zarrs-0.2.1.dist-info/RECORD
