Metadata-Version: 2.4
Name: zarrs
Version: 0.2.1
Classifier: Programming Language :: Rust
Classifier: Programming Language :: Python :: Implementation :: CPython
Classifier: Programming Language :: Python :: Implementation :: PyPy
Classifier: Typing :: Typed
Requires-Dist: numpy>=1.24
Requires-Dist: zarr>=3.1
License-File: LICENSE
Summary: A CodecPipeline for zarr-python backed by the zarrs Rust crate
Author: Ilan Gold, Lachlan Deakin, Philipp Angerer
License-Expression: MIT
Requires-Python: >=3.11
